dearpygui_grid.py
dearpygui_grid-1.0.1.dist-info/LICENSE
dearpygui_grid-1.0.1.dist-info/METADATA
dearpygui_grid-1.0.1.dist-info/WHEEL
dearpygui_grid-1.0.1.dist-info/top_level.txt
dearpygui_grid-1.0.1.dist-info/RECORD
