Metadata-Version: 2.1
Name: dearpygui-grid
Version: 1.0.1
Summary: Layout manager for Dear PyGui.
Author-email: Anthony Doupe <atlamillias@outlook.com>
Project-URL: Homepage, https://github.com/Atlamillias/DearPyGui-Grid
Classifier: Programming Language :: Python :: Implementation :: CPython
Classifier: Programming Language :: Python :: 3 :: Only
Classifier: Programming Language :: Python :: 3.10
Classifier: Operating System :: Microsoft :: Windows :: Windows 8.1
Classifier: Operating System :: Microsoft :: Windows :: Windows 10
Classifier: Operating System :: Microsoft :: Windows :: Windows 11
Classifier: Operating System :: MacOS
Classifier: Operating System :: POSIX
Classifier: Operating System :: Unix
Classifier: License :: OSI Approved :: MIT License
Requires-Python: >=3.10
License-File: LICENSE
Requires-Dist: dearpygui >=1.9.0
Requires-Dist: typing-extensions ; python_version < "3.12"
